{
  "vehicles": [
    {
      "model": {
        "make": "Honda",
        "name": "Accord",
        "year": 2023
      },
      "nickName": "Accord",
      "vin": "1HGCY2F56PA059578",
      "imei": "865612071401950",
      "stats": {
        "localTimeZone": "-0400",
        "lastUpdated": "2026-05-15T01:57:54.000Z",
        "odometer": 36356.7,
        "location": {
          "lat": 27.905298,
          "lon": -82.489889,
          "heading": 177,
          "address": null
        },
        "fuelLevel": 49.74727137666077,
        "isRunning": true,
        "speed": 31.7,
        "mil": {
          "milOn": false,
          "lastUpdated": "2026-05-15T01:31:30.000Z",
          "qualifiedDtcList": []
        }
      }
    }
  ],
  "updated_at": "2026-05-15T01:58:00.663915+00:00"
}