{
  "vehicles": [
    {
      "model": {
        "make": "Honda",
        "name": "Accord",
        "year": 2023
      },
      "nickName": "Accord",
      "vin": "1HGCY2F56PA059578",
      "imei": "865612071401950",
      "stats": {
        "localTimeZone": "-0400",
        "lastUpdated": "2026-06-04T14:30:02.000Z",
        "odometer": 37318.3,
        "location": {
          "lat": 27.258153,
          "lon": -82.520523,
          "heading": 137,
          "address": null
        },
        "fuelLevel": 89.99008962225004,
        "isRunning": true,
        "speed": 46,
        "mil": {
          "milOn": false,
          "lastUpdated": "2026-06-04T13:50:49.000Z",
          "qualifiedDtcList": []
        }
      }
    }
  ],
  "updated_at": "2026-06-04T14:30:26.317597+00:00"
}